bsbolt-1.6.0.data/purelib/bsbolt/__init__.py
bsbolt-1.6.0.data/purelib/bsbolt/__main__.py
bsbolt-1.6.0.data/purelib/bsbolt/Align/AlignReads.py
bsbolt-1.6.0.data/purelib/bsbolt/Align/__init__.py
bsbolt-1.6.0.data/purelib/bsbolt/CallMethylation/CallValues.py
bsbolt-1.6.0.data/purelib/bsbolt/CallMethylation/CallVector.py
bsbolt-1.6.0.data/purelib/bsbolt/CallMethylation/ProcessMethylationContigs.py
bsbolt-1.6.0.data/purelib/bsbolt/CallMethylation/__init__.py
bsbolt-1.6.0.data/purelib/bsbolt/External/BWA/bwa
bsbolt-1.6.0.data/purelib/bsbolt/External/HTSLIB/stream_bam
bsbolt-1.6.0.data/purelib/bsbolt/External/WGSIM/wgsim
bsbolt-1.6.0.data/purelib/bsbolt/Impute/__init__.py
bsbolt-1.6.0.data/purelib/bsbolt/Impute/kNN_Impute.py
bsbolt-1.6.0.data/purelib/bsbolt/Impute/Imputation/EuclideanDistance.py
bsbolt-1.6.0.data/purelib/bsbolt/Impute/Imputation/GenomeImputation.py
bsbolt-1.6.0.data/purelib/bsbolt/Impute/Imputation/GenomeImputationWindows.py
bsbolt-1.6.0.data/purelib/bsbolt/Impute/Imputation/__init__.py
bsbolt-1.6.0.data/purelib/bsbolt/Impute/Impute_Utils/ImputationFunctions.py
bsbolt-1.6.0.data/purelib/bsbolt/Impute/Impute_Utils/__init__.py
bsbolt-1.6.0.data/purelib/bsbolt/Impute/Validation/ImputationAssessment.py
bsbolt-1.6.0.data/purelib/bsbolt/Impute/Validation/MaskValues.py
bsbolt-1.6.0.data/purelib/bsbolt/Impute/Validation/__init__.py
bsbolt-1.6.0.data/purelib/bsbolt/Index/IndexOutput.py
bsbolt-1.6.0.data/purelib/bsbolt/Index/RRBSCutSites.py
bsbolt-1.6.0.data/purelib/bsbolt/Index/RRBSIndex.py
bsbolt-1.6.0.data/purelib/bsbolt/Index/WholeGenomeIndex.py
bsbolt-1.6.0.data/purelib/bsbolt/Index/__init__.py
bsbolt-1.6.0.data/purelib/bsbolt/Matrix/MatrixAggregator.py
bsbolt-1.6.0.data/purelib/bsbolt/Matrix/SiteAggregator.py
bsbolt-1.6.0.data/purelib/bsbolt/Matrix/SiteCounter.py
bsbolt-1.6.0.data/purelib/bsbolt/Matrix/__init__.py
bsbolt-1.6.0.data/purelib/bsbolt/Simulate/SetCyotsineMethylation.py
bsbolt-1.6.0.data/purelib/bsbolt/Simulate/SimulateMethylatedReads.py
bsbolt-1.6.0.dist-info/LICENSE
bsbolt-1.6.0.dist-info/METADATA
bsbolt-1.6.0.dist-info/WHEEL
bsbolt-1.6.0.dist-info/entry_points.txt
bsbolt-1.6.0.dist-info/top_level.txt
bsbolt-1.6.0.dist-info/RECORD
