Metadata-Version: 2.1
Name: bsbolt
Version: 1.6.0
Summary: Bisulfite Sequencing Processing Platform
Home-page: https://github.com/NuttyLogic/BSBolt
Author: Colin P. Farrell
Author-email: colinpfarrell@gmail.com
License: MIT
Project-URL: Documentation, https://bsbolt.readthedocs.io/en/latest/
Platform: Linux
Platform: Mac OS-X
Platform: Unix
Classifier: Programming Language :: Python :: 3.6
Classifier: Programming Language :: Python :: 3.7
Classifier: Programming Language :: Python :: 3.8
Requires: pysam
Requires: numpy
Requires: tqdm
Requires-Python: >=3.6
License-File: LICENSE
Requires-Dist: pysam (>=0.15.3)
Requires-Dist: numpy (>=1.16.3)
Requires-Dist: tqdm (>=4.31.1)
Requires-Dist: setuptools (>=46.0.0)
